xiaoapi_elasticsearch/__init__.py
xiaoapi_elasticsearch/elasticsearch.py
xiaoapi_elasticsearch-0.0.3.dist-info/LICENSE
xiaoapi_elasticsearch-0.0.3.dist-info/METADATA
xiaoapi_elasticsearch-0.0.3.dist-info/WHEEL
xiaoapi_elasticsearch-0.0.3.dist-info/top_level.txt
xiaoapi_elasticsearch-0.0.3.dist-info/RECORD
