Metadata-Version: 2.1
Name: xiaoapi-elasticsearch
Version: 0.0.3
Summary: xiaoapi elasticsearch
Author-email: xiaojinli <553555614@qq.com>
License: MIT
Project-URL: Documentation, https://github.com/xiaojinlii/xiaoapi/blob/main/libs/elasticsearch/README.md
Project-URL: Repository, https://github.com/xiaojinlii/xiaoapi
Project-URL: Source Code, https://github.com/xiaojinlii/xiaoapi/tree/main/libs/elasticsearch
Keywords: xiaoapi,fastapi,web-framework,elasticsearch
Classifier: Framework :: FastAPI
Classifier: Programming Language :: Python :: 3
Requires-Python: >=3.8
License-File: LICENSE
Requires-Dist: xiaoapi >=0.0.2
Requires-Dist: elasticsearch[async] ==8.11.0
